socketshark/__init__.py
socketshark/__main__.py
socketshark/config_defaults.py
socketshark/constants.py
socketshark/events.py
socketshark/exceptions.py
socketshark/receiver.py
socketshark/redis_connection.py
socketshark/session.py
socketshark/subscription.py
socketshark/utils.py
socketshark/backend/__init__.py
socketshark/backend/websockets.py
socketshark/metrics/__init__.py
socketshark/metrics/log.py
socketshark/metrics/prometheus.py
socketshark-0.4.0.dist-info/LICENSE
socketshark-0.4.0.dist-info/METADATA
socketshark-0.4.0.dist-info/WHEEL
socketshark-0.4.0.dist-info/entry_points.txt
socketshark-0.4.0.dist-info/top_level.txt
socketshark-0.4.0.dist-info/RECORD
