Metadata-Version: 2.1
Name: socketshark
Version: 0.4.0
Summary: WebSocket message router
Home-page: http://github.com/closeio/socketshark
License: MIT
Platform: any
Classifier: Intended Audience :: Developers
Classifier: License :: OSI Approved :: MIT License
Classifier: Operating System :: OS Independent
Classifier: Topic :: Software Development :: Libraries :: Python Modules
Classifier: Programming Language :: Python
Classifier: Programming Language :: Python :: 3
Classifier: Programming Language :: Python :: 3.8
Classifier: Programming Language :: Python :: 3.9
License-File: LICENSE
Requires-Dist: aiohttp
Requires-Dist: aioredis
Requires-Dist: click
Requires-Dist: structlog[dev]
Requires-Dist: websockets
